sketchingpy/__init__.py
sketchingpy/abstracted.py
sketchingpy/bezier_util.py
sketchingpy/const.py
sketchingpy/control_struct.py
sketchingpy/data_struct.py
sketchingpy/dialog_struct.py
sketchingpy/geo.py
sketchingpy/local_data_struct.py
sketchingpy/pillow_struct.py
sketchingpy/pillow_util.py
sketchingpy/py.typed
sketchingpy/pygame_prompt.py
sketchingpy/shape_struct.py
sketchingpy/sketch2d_keymap.py
sketchingpy/sketch2dapp.py
sketchingpy/sketch2dstatic.py
sketchingpy/sketch2dweb.py
sketchingpy/state_struct.py
sketchingpy/transform.py
sketchingpy/test/IBMPlexMono-Regular.ttf
sketchingpy/test/__init__.py
sketchingpy/test/test_abstracted.py
sketchingpy/test/test_bezier_util.py
sketchingpy/test/test_control_struct.py
sketchingpy/test/test_geo.py
sketchingpy/test/test_local_data_struct.py
sketchingpy/test/test_pillow_struct.py
sketchingpy/test/test_pillow_util.py
sketchingpy/test/test_shape_struct.py
sketchingpy/test/test_sketch2d_keymap.py
sketchingpy/test/test_state_struct.py
sketchingpy/test/test_transform.py
sketchingpy-0.3.2.dist-info/METADATA
sketchingpy-0.3.2.dist-info/WHEEL
sketchingpy-0.3.2.dist-info/licenses/LICENSE.md
sketchingpy-0.3.2.dist-info/RECORD
