Metadata-Version: 2.4
Name: sketchingpy
Version: 0.3.2
Summary: Tools for quick creative programmig.
Project-URL: Homepage, https://sketchingpy.org
Project-URL: Documentation, https://sketchingpy.org/reference
Project-URL: Source, https://codeberg.org/sketchingpy/Sketchingpy
Project-URL: Issue Tracker, https://codeberg.org/sketchingpy/Sketchingpy/issues
Project-URL: Changelog, https://codeberg.org/sketchingpy/Sketchingpy/commits/branch/main
Author-email: A Samuel Pottinger <hello@sketchingpy.org>
License-File: LICENSE.md
Classifier: Development Status :: 4 - Beta
Classifier: License :: OSI Approved :: BSD License
Classifier: Operating System :: OS Independent
Classifier: Programming Language :: Python :: 3
Classifier: Topic :: Games/Entertainment
Classifier: Topic :: Multimedia
Classifier: Topic :: Multimedia :: Graphics
Classifier: Topic :: Scientific/Engineering :: Visualization
Requires-Python: >=3.7
Provides-Extra: desktop
Requires-Dist: numpy>=1.26.2; extra == 'desktop'
Requires-Dist: pillow>=10.3.0; extra == 'desktop'
Requires-Dist: pygame-ce>=2.5.0; extra == 'desktop'
Provides-Extra: desktopall
Requires-Dist: bezier>=2024.6.20; extra == 'desktopall'
Requires-Dist: numpy>=1.26.2; extra == 'desktopall'
Requires-Dist: pillow>=10.3.0; extra == 'desktopall'
Requires-Dist: pygame-ce>=2.5.0; extra == 'desktopall'
Requires-Dist: pygame-gui>=0.6.9; extra == 'desktopall'
Provides-Extra: dev
Requires-Dist: bezier>=2024.6.20; extra == 'dev'
Requires-Dist: jinja2>=3.1.2; extra == 'dev'
Requires-Dist: mypy>=1.8.0; extra == 'dev'
Requires-Dist: nose2>=0.14.0; extra == 'dev'
Requires-Dist: pdoc>=14.3.0; extra == 'dev'
Requires-Dist: pycodestyle>=2.11.1; extra == 'dev'
Requires-Dist: pyflakes>=3.1.0; extra == 'dev'
Requires-Dist: pygame-ce>=2.5.0; extra == 'dev'
Requires-Dist: pygame-gui>=0.6.9; extra == 'dev'
Requires-Dist: pyyaml>=6.0.1; extra == 'dev'
Requires-Dist: selenium>=4.16.0; extra == 'dev'
Requires-Dist: types-pillow>=10.1.0.2; extra == 'dev'
Provides-Extra: minimal
Requires-Dist: pillow>=10.3.0; extra == 'minimal'
Provides-Extra: notebook
Requires-Dist: bezier>=2024.6.20; extra == 'notebook'
Requires-Dist: numpy>=1.26.2; extra == 'notebook'
Requires-Dist: pillow>=10.3.0; extra == 'notebook'
Provides-Extra: static
Requires-Dist: bezier>=2024.6.20; extra == 'static'
Requires-Dist: numpy>=1.26.2; extra == 'static'
Requires-Dist: pillow>=10.3.0; extra == 'static'
